mycalcpackage/__init__.py
mycalcpackage/calculator.py
mycalcpackage-0.1.1.dist-info/METADATA
mycalcpackage-0.1.1.dist-info/WHEEL
mycalcpackage-0.1.1.dist-info/entry_points.txt
mycalcpackage-0.1.1.dist-info/top_level.txt
mycalcpackage-0.1.1.dist-info/RECORD
